readfish_tools-0.0.1.dist-info/METADATA
readfish_tools-0.0.1.dist-info/WHEEL
readfish_tools/__init__.py
readfish_tools/readfish_tools.pypy39-pp73-x86-linux-gnu.so
readfish_tools-0.0.1.dist-info/RECORD
