Metadata-Version: 2.1
Name: readfish-tools
Version: 0.0.1
Classifier: Programming Language :: Rust
Classifier: Programming Language :: Python :: Implementation :: CPython
Classifier: Programming Language :: Python :: Implementation :: PyPy
Classifier: Intended Audience :: Science/Research
Classifier: Programming Language :: Python :: 3.8
Classifier: Programming Language :: Python :: 3.9
Classifier: Programming Language :: Python :: 3.10
Classifier: Programming Language :: Python :: 3.11
Requires-Dist: pytest ; extra == 'tests'
Requires-Dist: mappy_rs ; extra == 'tests'
Requires-Dist: mappy ; extra == 'tests'
Provides-Extra: tests
Summary: A blazingly fast Python library for reading and summarising readfish output
Keywords: bioinformatics,python,rust,readfish,analysis
Author: Rory Munro <roryjmunro1@gmail.com>
Author-email: Rory Munro <rory.munro@nottingham.ac.uk>
Maintainer-email: Rory Munro <rory.munro@nottingham.ac.uk>
License: BSD 3-Clause License
Requires-Python: >=3.8
Project-URL: Source Code, https://github.com/adoni5/readfish-tools/
